MANIFEST.in
setup.py
docs/CONTRIBUTORS.txt
docs/HISTORY.txt
docs/README.txt
src/templer/__init__.py
src/templer.ztfy.egg-info/PKG-INFO
src/templer.ztfy.egg-info/SOURCES.txt
src/templer.ztfy.egg-info/dependency_links.txt
src/templer.ztfy.egg-info/entry_points.txt
src/templer.ztfy.egg-info/namespace_packages.txt
src/templer.ztfy.egg-info/not-zip-safe
src/templer.ztfy.egg-info/requires.txt
src/templer.ztfy.egg-info/top_level.txt
src/templer/ztfy/__init__.py
src/templer/ztfy/package.py
src/templer/ztfy/templates/ztfy_package/.hgignore
src/templer/ztfy/templates/ztfy_package/MANIFEST.in
src/templer/ztfy/templates/ztfy_package/bootstrap.py
src/templer/ztfy/templates/ztfy_package/buildout.cfg_tmpl
src/templer/ztfy/templates/ztfy_package/setup.py_tmpl
src/templer/ztfy/templates/ztfy_package/docs/CONTRIBUTORS.txt_tmpl
src/templer/ztfy/templates/ztfy_package/docs/HISTORY.txt_tmpl
src/templer/ztfy/templates/ztfy_package/docs/README.txt_tmpl
src/templer/ztfy/templates/ztfy_package/src/+namespace_package+/__init__.py
src/templer/ztfy/templates/ztfy_package/src/+namespace_package+/+package+/__init__.py_tmpl
src/templer/ztfy/templates/ztfy_package/src/+namespace_package+/+package+/configure.zcml_tmpl
src/templer/ztfy/templates/ztfy_package/src/+namespace_package+/+package+/browser/__init__.py
src/templer/ztfy/templates/ztfy_package/src/+namespace_package+/+package+/browser/configure.zcml_tmpl
src/templer/ztfy/templates/ztfy_package/src/+namespace_package+/+package+/doctests/README.txt_tmpl
src/templer/ztfy/templates/ztfy_package/src/+namespace_package+/+package+/locales/+namespace_package+.+package+.pot
src/templer/ztfy/templates/ztfy_package/src/+namespace_package+/+package+/locales/en/LC_MESSAGES/+namespace_package+.+package+.po
src/templer/ztfy/templates/ztfy_package/src/+namespace_package+/+package+/tests/__init__.py
src/templer/ztfy/templates/ztfy_package/src/+namespace_package+/+package+/tests/test_docs.py_tmpl
src/templer/ztfy/templates/ztfy_package/src/+namespace_package+/+package+/tests/test_docstrings.py_tmpl